dbt/__init__.py
dbt/adapters/__init__.py
dbt/adapters/materialize/__init__.py
dbt/adapters/materialize/__version__.py
dbt/adapters/materialize/connections.py
dbt/adapters/materialize/impl.py
dbt/include/__init__.py
dbt/include/materialize/__init__.py
dbt/include/materialize/dbt_project.yml
dbt/include/materialize/macros/adapters.sql
dbt/include/materialize/macros/catalog.sql
dbt/include/materialize/macros/mz_create_index.sql
dbt/include/materialize/macros/mz_create_sink.sql
dbt/include/materialize/macros/mz_create_source.sql
dbt/include/materialize/macros/mz_drop_index.sql
dbt/include/materialize/macros/mz_drop_sink.sql
dbt/include/materialize/macros/mz_drop_source.sql
dbt/include/materialize/macros/mz_generate_name.sql
dbt/include/materialize/macros/relations.sql
dbt/include/materialize/macros/materializations/helpers.sql
dbt/include/materialize/macros/materializations/incremental.sql
dbt/include/materialize/macros/materializations/materialized_view.sql
dbt/include/materialize/macros/materializations/random.sql
dbt/include/materialize/macros/materializations/seed.sql
dbt/include/materialize/macros/materializations/table.sql
dbt/include/materialize/macros/materializations/view.sql
dbt_materialize-0.20.1.dist-info/METADATA
dbt_materialize-0.20.1.dist-info/WHEEL
dbt_materialize-0.20.1.dist-info/top_level.txt
dbt_materialize-0.20.1.dist-info/RECORD
