Metadata-Version: 2.1
Name: dbt-materialize
Version: 0.20.1
Summary: The Materialize adapter plugin for dbt (data build tool).
Home-page: https://github.com/MaterializeInc/dbt-materialize
Author: Materialize, Inc.
Author-email: support@materialize.io
License: UNKNOWN
Platform: UNKNOWN
Requires-Dist: dbt-postgres (==0.20.1)
